{"stats":{"minecraft:mined":{"gemmod:sapphire_ore":1,"gemmod:ruby_ore":14,"minecraft:andesite":2,"minecraft:stripped_oak_wood":1,"minecraft:oak_wood":3,"minecraft:grass_block":24,"gemmod:sapphire_block":1,"gemmod:ruby_block":6,"minecraft:dirt":5},"minecraft:killed":{"minecraft:chicken":10,"minecraft:iron_golem":2,"minecraft:slime":32,"minecraft:cow":4},"minecraft:picked_up":{"minecraft:feather":4,"gemmod:ruby_ore":11,"minecraft:chicken":6,"minecraft:andesite":2,"minecraft:leather":2,"gemmod:sapphire_pickaxe":1,"gemmod:ruby":1,"minecraft:conduit":1,"minecraft:grass_block":1,"minecraft:dirt":28,"gemmod:sapphire_block":1,"minecraft:oak_wood":3,"gemmod:sapphire_sword":1,"gemmod:sapphire_ore":2,"minecraft:slime_ball":5,"minecraft:iron_ingot":12,"gemmod:ruby_block":3,"minecraft:beef":4,"minecraft:stripped_oak_wood":1,"minecraft:poppy":2,"gemmod:sapphire":4,"minecraft:egg":2},"minecraft:dropped":{"minecraft:iron_ingot":4,"gemmod:sapphire_ore":2,"minecraft:conduit":1,"gemmod:sapphire":3,"minecraft:grass_block":1},"minecraft:used":{"minecraft:dark_oak_planks":378,"minecraft:brick_wall":40,"gemmod:ruby_axe":42,"minecraft:command_block":12,"gemmod:ruby_block":15,"gemmod:sapphire_block":13,"minecraft:armor_stand":16,"minecraft:grass_block":49,"minecraft:polished_andesite":23,"minecraft:stone_button":4,"minecraft:oak_sign":12,"gemmod:ruby_pickaxe":22,"minecraft:chest":5,"minecraft:polished_granite":27,"gemmod:sapphire_sword":10,"gemmod:ruby_shovel":34,"minecraft:item_frame":15,"minecraft:conduit":20,"gemmod:ruby_ore":28,"minecraft:diamond_sword":15,"gemmod:sapphire_pickaxe":2,"minecraft:anvil":1,"gemmod:sapphire_ore":19,"minecraft:trapped_chest":1,"minecraft:andesite":2,"minecraft:oak_wood":4,"gemmod:ruby_hoe":7,"minecraft:stone_pressure_plate":8,"gemmod:ruby_sword":27,"minecraft:polished_diorite":111},"minecraft:custom":{"minecraft:time_since_rest":90869,"minecraft:sprint_one_cm":82691,"minecraft:walk_one_cm":282585,"minecraft:mob_kills":48,"minecraft:trigger_trapped_chest":22,"minecraft:interact_with_anvil":2,"minecraft:drop":11,"minecraft:damage_dealt":3971,"minecraft:fly_one_cm":92246,"minecraft:open_chest":30,"minecraft:play_one_minute":90869,"minecraft:crouch_one_cm":2151,"minecraft:sneak_time":2101,"minecraft:jump":257,"minecraft:leave_game":12,"minecraft:time_since_death":90869,"minecraft:fall_one_cm":418}},"DataVersion":2230}